django_uzbplaces-0.5.dist-info/DESCRIPTION.rst
django_uzbplaces-0.5.dist-info/METADATA
django_uzbplaces-0.5.dist-info/RECORD
django_uzbplaces-0.5.dist-info/WHEEL
django_uzbplaces-0.5.dist-info/metadata.json
django_uzbplaces-0.5.dist-info/top_level.txt
uzbplaces/__init__.py
uzbplaces/admin.py
uzbplaces/apps.py
uzbplaces/models.py
uzbplaces/serializers.py
uzbplaces/tests.py
uzbplaces/translation.py
uzbplaces/urls.py
uzbplaces/views.py
uzbplaces/fixtures/__init__.py
uzbplaces/fixtures/places.json
uzbplaces/management/__init__.py
uzbplaces/management/commands/__init__.py
uzbplaces/management/commands/populate_data.py
uzbplaces/migrations/0001_initial.py
uzbplaces/migrations/0002_auto_20161129_2012.py
uzbplaces/migrations/__init__.py
