Metadata-Version: 2.0
Name: django-uzbplaces
Version: 0.5
Summary: UzbPlaces is a simple Django app to integrate places in Uzbekistan.
Home-page: https://github.com/MrBrownWins/uzbplaces
Author: Mukhammad Karimov
Author-email: hey@karimoff.me
License: MIT License
Keywords: sample django places development
Platform: UNKNOWN
Classifier: Environment :: Web Environment
Classifier: Framework :: Django
Classifier: Framework :: Django :: 1.11
Classifier: Intended Audience :: Developers
Classifier: License :: OSI Approved :: BSD License
Classifier: Operating System :: OS Independent
Classifier: Programming Language :: Python
Classifier: Programming Language :: Python :: 3
Classifier: Programming Language :: Python :: 3.4
Classifier: Programming Language :: Python :: 3.5
Classifier: Topic :: Internet :: WWW/HTTP
Classifier: Topic :: Internet :: WWW/HTTP :: Dynamic Content
Requires-Dist: django-modeltranslation
Requires-Dist: django-geoposition
